README.md
setup.py
succinct/VERSION
succinct/__init__.py
succinct/bits.py
succinct/compressed_runs_bit_array.py
succinct/elias_fano_bit_array.py
succinct/eliasfano.py
succinct/louds.py
succinct/permutation.py
succinct/poppy.py
succinct/py.typed
succinct/rle_bit_array.py
succinct/string_index.py
succinct.egg-info/PKG-INFO
succinct.egg-info/SOURCES.txt
succinct.egg-info/dependency_links.txt
succinct.egg-info/requires.txt
succinct.egg-info/top_level.txt