Metadata-Version: 2.1
Name: succinct
Version: 0.0.7
Summary: Succinct, compact, and compressed data structures for data-intensive applications
Home-page: https://github.com/miiohio/succinct
Author: William Harvey
Author-email: drwjharvey@gmail.com
License: UNKNOWN
Platform: UNKNOWN
